algoutils.py
algoutils-0.0.3.dist-info/LICENSE
algoutils-0.0.3.dist-info/METADATA
algoutils-0.0.3.dist-info/WHEEL
algoutils-0.0.3.dist-info/top_level.txt
algoutils-0.0.3.dist-info/RECORD
